{"MP":["1","1","1","1","1","1","1","1","2","2","3","3","3","6","8","9","10","10","13","14","16","17","20","21","21","23","24","25","26","28","28","29","29","29","29","30","30","30","30","30"],"starts":["0","0","1","1","1","1","1","1","2","2","2","3","3","6","7","9","9","10","13","14","16","17","20","21","21","23","24","25","26","28","28","29","29","29","29","29","30","30","30","30"],"mins":["5","66","74","90","90","90","90","90","154","180","180","270","270","540","713","810","858","900","1170","1260","1440","1530","1800","1842","1890","1987","2160","2250","2340","2406","2520","2610","2610","2610","2610","2693","2700","2700","2700","2700"],"_90s":["0.1","0.7","0.8","1.0","1.0","1.0","1.0","1.0","1.7","2.0","2.0","3.0","3.0","6.0","7.9","9.0","9.5","10.0","13.0","14.0","16.0","17.0","20.0","20.5","21.0","22.1","24.0","25.0","26.0","26.7","28.0","29.0","29.0","29.0","29.0","29.9","30.0","30.0","30.0","30.0"],"goals":["0","0","0","0","0","0","0","0","0","0","0","0","0","0","0","0","0","0","0","0","0","0","0","0","0","0","0","0","0","0","0","0","0","0","0","0","0","0","0","0"],"assists":["0","0","0","0","0","0","0","0","0","0","0","0","0","0","0","0","0","0","0","0","0","0","0","0","0","0","0","0","0","0","0","0","0","0","0","0","0","1","1","1"],"GplusA":["0","0","0","0","0","0","0","0","0","0","0","0","0","0","0","0","0","0","0","0","0","0","0","0","0","0","0","0","0","0","0","0","0","0","0","0","0","1","1","1"],"GminusPK":["0","0","0","0","0","0","0","0","0","0","0","0","0","0","0","0","0","0","0","0","0","0","0","0","0","0","0","0","0","0","0","0","0","0","0","0","0","0","0","0"],"PK":["0","0","0","0","0","0","0","0","0","0","0","0","0","0","0","0","0","0","0","0","0","0","0","0","0","0","0","0","0","0","0","0","0","0","0","0","0","0","0","0"],"PKatt":["0","0","0","0","0","0","0","0","0","0","0","0","0","0","0","0","0","0","0","0","0","0","0","0","0","0","0","0","0","0","0","0","0","0","0","0","0","0","0","0"],"yellow":["0","0","0","0","0","0","0","0","0","0","0","0","0","0","0","0","0","0","0","0","0","0","0","0","0","0","0","1","1","1","1","1","1","1","1","1","3","3","3","4"],"red":["0","0","0","0","0","0","0","0","0","0","0","0","0","0","0","0","0","0","0","0","0","0","0","0","0","0","0","0","0","0","0","0","0","0","0","0","0","0","1","1"],"xG":["0.0","0.0","0.0","0.0","0.0","0.0","0.0","0.0","0.0","0.0","0.0","0.0","0.0","0.0","0.0","0.0","0.0","0.0","0.0","0.0","0.0","0.0","0.0","0.0","0.0","0.0","0.0","0.0","0.0","0.0","0.0","0.0","0.0","0.0","0.0","0.0","0.0","0.0","0.0","0.0"],"npxG":["0.0","0.0","0.0","0.0","0.0","0.0","0.0","0.0","0.0","0.0","0.0","0.0","0.0","0.0","0.0","0.0","0.0","0.0","0.0","0.0","0.0","0.0","0.0","0.0","0.0","0.0","0.0","0.0","0.0","0.0","0.0","0.0","0.0","0.0","0.0","0.0","0.0","0.0","0.0","0.0"],"xAG":["0.0","0.0","0.0","0.0","0.0","0.0","0.0","0.0","0.0","0.0","0.0","0.0","0.0","0.0","0.0","0.0","0.0","0.0","0.0","0.0","0.0","0.0","0.0","0.0","0.0","0.0","0.0","0.0","0.0","0.0","0.0","0.0","0.0","0.0","0.1","0.1","0.1","0.1","0.4","0.5"],"npxGxAG":[null,null,null,null,null,null,null,null,null,null,null,null,null,null,null,null,null,null,null,null,null,null,null,null,null,null,null,null,null,null,null,null,null,null,null,null,null,null,null,null],"npxGplusxAG":["0.0","0.0","0.0","0.0","0.0","0.0","0.0","0.0","0.0","0.0","0.0","0.0","0.0","0.0","0.0","0.0","0.0","0.0","0.0","0.0","0.0","0.0","0.0","0.0","0.0","0.0","0.0","0.0","0.0","0.0","0.0","0.0","0.0","0.0","0.1","0.1","0.1","0.1","0.4","0.5"],"prgC":["0","0","0","0","0","0","0","0","0","0","0","0","0","0","0","0","0","0","0","0","0","0","0","0","0","0","0","0","0","0","0","0","0","0","0","0","0","0","0","0"],"prgP":["0","0","0","0","0","0","0","0","0","0","0","0","0","0","0","0","0","0","0","0","0","0","0","0","0","0","0","0","0","0","0","0","0","0","0","1","1","1","2","2"],"prgR":["0","0","0","0","0","0","0","0","0","0","0","0","0","0","0","0","0","0","0","0","0","0","0","0","0","0","0","0","0","0","0","0","0","0","0","0","0","0","0","0"],"g90":["0.00","0.00","0.00","0.00","0.00","0.00","0.00","0.00","0.00","0.00","0.00","0.00","0.00","0.00","0.00","0.00","0.00","0.00","0.00","0.00","0.00","0.00","0.00","0.00","0.00","0.00","0.00","0.00","0.00","0.00","0.00","0.00","0.00","0.00","0.00","0.00","0.00","0.00","0.00","0.00"],"a90":["0.00","0.00","0.00","0.00","0.00","0.00","0.00","0.00","0.00","0.00","0.00","0.00","0.00","0.00","0.00","0.00","0.00","0.00","0.00","0.00","0.00","0.00","0.00","0.00","0.00","0.00","0.00","0.00","0.00","0.00","0.00","0.00","0.00","0.00","0.00","0.00","0.00","0.04","0.05","0.06"]}